pysenti/__init__.py
pysenti/original/SentiStrength.jar
pysenti/original/data/BoosterWordList.txt
pysenti/original/data/EmoticonLookupTable.txt
pysenti/original/data/EmotionLookupTable.txt
pysenti/original/data/EnglishWordList.txt
pysenti/original/data/IdiomLookupTable.txt
pysenti/original/data/NegatingWordList.txt
pysenti/original/data/QuestionWords.txt
pysenti/original/data/SlangLookupTable.txt
PySentiStrength-1.0.1.dist-info/METADATA
PySentiStrength-1.0.1.dist-info/WHEEL
PySentiStrength-1.0.1.dist-info/top_level.txt
PySentiStrength-1.0.1.dist-info/RECORD
