Metadata-Version: 2.1
Name: PySentiStrength
Version: 1.0.1
Summary: Python 3 Wrapper for SentiStrength
Home-page: https://github.com/hykilpikonna/PySenti
Author: Azalea Gui, Mike Thelwall
Author-email: me@hydev.org, m.thelwall@wlv.ac.uk
License: UNKNOWN
Platform: UNKNOWN
Classifier: Operating System :: OS Independent
Classifier: Programming Language :: Python :: 3
Classifier: Programming Language :: Python :: 3.7
Classifier: Programming Language :: Python :: 3.8
Classifier: Programming Language :: Python :: 3.9
Classifier: Programming Language :: Python :: 3.10
Requires-Dist: setuptools
Requires-Dist: typing-extensions
